verlib2/__init__.py
verlib2/_structures.py
verlib2/version.py
verlib2-0.2.1.dist-info/LICENSE
verlib2-0.2.1.dist-info/METADATA
verlib2-0.2.1.dist-info/WHEEL
verlib2-0.2.1.dist-info/top_level.txt
verlib2-0.2.1.dist-info/RECORD
