Metadata-Version: 2.2
Name: verlib2
Version: 0.2.1
Summary: A standalone variant of packaging.version, without anything else.
Author-email: Donald Stufft <donald@stufft.io>
Maintainer-email: Andreas Motl <andreas.motl@panodata.org>
License: Apache License 2.0
Project-URL: Repository, https://github.com/pyveci/verlib2
Keywords: distutils,packaging,version
Classifier: Development Status :: 5 - Production/Stable
Classifier: Intended Audience :: Developers
Classifier: License :: OSI Approved :: Apache Software License
Classifier: License :: OSI Approved :: BSD License
Classifier: Programming Language :: Python
Classifier: Programming Language :: Python :: 3 :: Only
Classifier: Programming Language :: Python :: 3.6
Classifier: Programming Language :: Python :: 3.7
Classifier: Programming Language :: Python :: 3.8
Classifier: Programming Language :: Python :: 3.9
Classifier: Programming Language :: Python :: 3.10
Classifier: Programming Language :: Python :: 3.11
Classifier: Programming Language :: Python :: 3.12
Classifier: Programming Language :: Python :: 3.13
Classifier: Programming Language :: Python :: Implementation :: CPython
Classifier: Programming Language :: Python :: Implementation :: PyPy
Classifier: Typing :: Typed
Requires-Python: >=3.6
License-File: LICENSE
Provides-Extra: develop
Requires-Dist: black<26; extra == "develop"
Requires-Dist: mypy<1.15; extra == "develop"
Requires-Dist: poethepoet<1; extra == "develop"
Requires-Dist: pyproject-fmt<2.6; extra == "develop"
Requires-Dist: ruff<0.10; extra == "develop"
Requires-Dist: validate-pyproject<0.24; extra == "develop"
Provides-Extra: release
Requires-Dist: build<2; extra == "release"
Requires-Dist: twine<7; extra == "release"
Provides-Extra: test
Requires-Dist: pretend<2; extra == "test"
Requires-Dist: pytest<9; extra == "test"
Requires-Dist: pytest-cov<7; extra == "test"
